[{"place_id": 289097130, "licence": "Data \u00a9 OpenStreetMap contributors, ODbL 1.0. http://osm.org/copyright", "osm_type": "node", "osm_id": 4263514163, "lat": "21.9176869", "lon": "-101.9639427", "class": "place", "type": "town", "place_rank": 18, "importance": 0.16004000076295108, "addresstype": "town", "name": "Palo Alto", "display_name": "Palo Alto, El Llano, Aguascalientes, 20361, Mexico", "boundingbox": ["21.8776869", "21.9576869", "-102.0039427", "-101.9239427"], "geojson": {"type": "Point", "coordinates": [-101.9639427, 21.9176869]}}, {"place_id": 289039357, "licence": "Data \u00a9 OpenStreetMap contributors, ODbL 1.0. http://osm.org/copyright", "osm_type": "way", "osm_id": 1051108968, "lat": "21.8821141", "lon": "-102.25045115", "class": "highway", "type": "residential", "place_rank": 26, "importance": 0.05339261081864649, "addresstype": "road", "name": "Palo Alto", "display_name": "Palo Alto, Aguascalientes City, Municipio de Aguascalientes, Aguascalientes, 20133, Mexico", "boundingbox": ["21.8820950", "21.8821332", "-102.2504921", "-102.2504102"], "geojson": {"type": "LineString", "coordinates": [[-102.2504921, 21.882095], [-102.2504102, 21.8821332]]}}]